{
  "id": "learning-languages/go",
  "title": "GOLANG",
  "description": "---",
  "source": "@site/docs/learning-languages/go.md",
  "sourceDirName": "learning-languages",
  "slug": "/learning-languages/go",
  "permalink": "/docs/learning-languages/go",
  "draft": false,
  "unlisted": false,
  "tags": [],
  "version": "current",
  "frontMatter": {},
  "sidebar": "tutorialSidebar",
  "previous": {
    "title": "Databases",
    "permalink": "/docs/learning-languages/databases"
  },
  "next": {
    "title": "Python",
    "permalink": "/docs/learning-languages/python"
  }
}